uc_browser_scrapy/__init__.py
uc_browser_scrapy/http.py
uc_browser_scrapy/middlewares.py
uc_browser_scrapy-0.1.6.dist-info/WHEEL
uc_browser_scrapy-0.1.6.dist-info/METADATA
uc_browser_scrapy-0.1.6.dist-info/RECORD
